randist/__init__.py
randist/randist.py
randist/modules/Nregion.py
randist/modules/Nregions.py
randist/modules/Sregions.py
randist/modules/__init__.py
randist/modules/basicInfo.py
randist/modules/commonFuncs.py
randist/modules/dataCollector.py
randist/modules/enums.py
randist/modules/formulas.py
randist/modules/numericFuncs.py
randist/modules/phis.py
randist/modules/plot.py
randist/modules/region.py
randist/modules/serializedFormula.py
randist/modules/pyprelude/EasyWriter.py
randist/modules/pyprelude/FPToolBox.py
randist/modules/pyprelude/GraphGen.py
randist/modules/pyprelude/Memorization.py
randist/modules/pyprelude/Progress.py
randist/modules/pyprelude/StringTools.py
randist/modules/pyprelude/TableReader.py
randist/modules/pyprelude/TableWriter.py
randist/modules/pyprelude/Timer.py
randist/modules/pyprelude/__init__.py
randist-1.1.7.dist-info/LICENSE
randist-1.1.7.dist-info/METADATA
randist-1.1.7.dist-info/WHEEL
randist-1.1.7.dist-info/top_level.txt
randist-1.1.7.dist-info/RECORD
