Metadata-Version: 2.1
Name: randist
Version: 1.1.7
Summary: Distance statistics for two random events on a network
Home-page: https://github.com/tidues/Distance-Distribution-of-Random-Events
Author: Ningji Wei
Author-email: tidues@gmail.com
License: UNKNOWN
Platform: UNKNOWN
Classifier: Programming Language :: Python :: 3
Classifier: License :: OSI Approved :: MIT License
Classifier: Operating System :: OS Independent
